units_llnl/__init__.py
units_llnl/units_llnl_ext.abi3.so
units_llnl-0.13.1.dist-info/METADATA
units_llnl-0.13.1.dist-info/WHEEL
units_llnl-0.13.1.dist-info/RECORD
units_llnl-0.13.1.dist-info/licenses/LICENSE
units_llnl-0.13.1.dist-info/licenses/NOTICE
