Metadata-Version: 2.4
Name: units_llnl
Version: 0.13.1
Summary: Python bindings for the LLNL units library
Keywords: units,measurement,power systems,co-simulation,commodities,science,python
Author-Email: Philip Top <top1@llnl.gov>
License-Expression: BSD-3-Clause
License-File: LICENSE
License-File: NOTICE
Classifier: Programming Language :: Python :: 3
Classifier: Operating System :: OS Independent
Classifier: Topic :: Scientific/Engineering
Classifier: Development Status :: 4 - Beta
Project-URL: Homepage, https://github.com/llnl/units
Project-URL: Documentation, https://units.readthedocs.io/en/latest/
Project-URL: Repository, https://github.com/llnl/units
Project-URL: Issues, https://github.com/LLNL/units/issues
Project-URL: Changelog, https://github.com/LLNL/units/blob/main/CHANGELOG.md
Requires-Python: >=3.10
Provides-Extra: test
Requires-Dist: pytest; extra == "test"
